Workbook
Name Slicer_Category: #N/A
Name Slicer_Customer: #N/A
Name Slicer_Supplier: #N/A

Sheet Dashboard
O1: Data Till - | P1: 46225
B2: Inventory Management & Stock Analysis Dashboard
B5: 📦 Total Products | F5: 🏬 Inventory Value | J5: 📚 Inventory Count | N5: ⚠ Low Stock
B6: =Calculations!B3 -> 25 | F6: =Calculations!B4 -> 1297755 | J6: =Calculations!B5 -> 3643 | N6: =Calculations!B6 -> 0
B11: 🚫 Out of Stock | F11: 🛒 Purchases | J11: 💰 Sales | N11: 📈 Potential Gross Profit
B12: =Calculations!B7 -> 0 | F12: =Calculations!B8 -> 903800 | J12: =Calculations!B9 -> 866550 | N12: =Calculations!B10 -> 646095

Sheet Calculations
A2: KPI | B2: Hint
A3: Total Products | B3: =COUNTA(tblProducts[Product ID]) -> 25
A4: Inventory Value | B4: =SUM(tblInventoryReport[Inventory Value]) -> 1297755 | E4: Sales Value of Current Stock
A5: Units in Stock | B5: =SUM(tblInventoryReport[Current Stock]) -> 3643 | E5: =Products!F2*'Inventory Report'!I2 -> 99450
A6: Low Stock | B6: =COUNTIF(tblInventoryReport[Stock Status],"Low Stock") -> 0 | E6: =Products!F3*'Inventory Report'!I3 -> 143000
A7: Out of Stock | B7: =COUNTIF(tblInventoryReport[Stock Status],"Out of Stock") -> 0 | E7: =Products!F4*'Inventory Report'!I4 -> 112750
A8: Purchase Value | B8: =SUM(tblPurchases[Total Cost]) -> 903800 | E8: =Products!F5*'Inventory Report'!I5 -> 222600
A9: Sales Value | B9: =SUM(tblSales[Total Sales]) -> 866550 | E9: =Products!F6*'Inventory Report'!I6 -> 73850
A10: Estimated Profit in Inventory | B10: =SUM(tblSalesValueCurrentStock[[Sales Value of Current Stock ]])-SUM(tblInventoryReport[Inventory Value]) -> 646095 | E10: =Products!F7*'Inventory Report'!I7 -> 28960
E11: =Products!F8*'Inventory Report'!I8 -> 19000
E12: =Products!F9*'Inventory Report'!I9 -> 23760
E13: =Products!F10*'Inventory Report'!I10 -> 54080
E14: =Products!F11*'Inventory Report'!I11 -> 17440
E15: =Products!F12*'Inventory Report'!I12 -> 170000
E16: =Products!F13*'Inventory Report'!I13 -> 161200
E17: =Products!F14*'Inventory Report'!I14 -> 84000
E18: =Products!F15*'Inventory Report'!I15 -> 60800
E19: =Products!F16*'Inventory Report'!I16 -> 163800
E20: =Products!F17*'Inventory Report'!I17 -> 49500
E21: =Products!F18*'Inventory Report'!I18 -> 78000
E22: =Products!F19*'Inventory Report'!I19 -> 27000
... E29: =Products!F26*'Inventory Report'!I26 -> 39520

Sheet Pivot Table
A2: Row Labels | B2: Sum of Current Stock | F2: Row Labels | G2: Sum of Inventory Value
A3: Accessories | B3: 539 | F3: External Hard Drive 1TB | G3: 169600
A4: Electronics | B4: 1059 | F4: Storage Cabinet | G4: 121800
A5: Furniture | B5: 165 | F5: Office Chair | G5: 119000
A6: Stationery | B6: 1880 | F6: Study Table | G6: 109200
A7: Grand Total | B7: 3643 | F7: Wireless Keyboard | G7: 99000
F8: USB Flash Drive 32GB | G8: 71750
F9: Bluetooth Speaker | G9: 69300
F10: Wireless Mouse | G10: 68850
F11: Power Bank 10000mAh | G11: 60800
F12: Bookshelf | G12: 56000
F13: Grand Total | G13: 945300
A15: Row Labels | B15: Sum of Total Cost | F15: Row Labels | G15: Sum of Total Sales
A16: Jan | B16: 321500 | F16: Jan | G16: 150800
A17: Feb | B17: 157100 | F17: Feb | G17: 109850
A18: Mar | B18: 207340 | F18: Mar | G18: 220250
A19: Apr | B19: 217860 | F19: Apr | G19: 215070
A20: Grand Total | B20: 903800 | F20: May | G20: 170580
F21: Grand Total | G21: 866550

Sheet Purchase Orders
A1: PO No | B1: Date | C1: Supplier | D1: Product ID | E1: Product | F1: Qty Purchased | G1: Cost Price | H1: Total Cost
A2: PO001 | B2: 46023 | C2: TechSource India | D2: P001 | E2: =IF(tblPurchases[[#This Row],[Product ID]]="","",_xlfn.XLOOKUP(tblPurchases[[#This Row],[Product ID]],tblProducts[Product ID],tblProducts[Product Name])) -> Wireless Mouse | F2: 50 | G2: =IF(tblPurchases[[#This Row],[Product ID]] ="","",_xlfn.XLOOKUP(tblPurchases[[#This Row],[Product]],tblProducts[Product Name],tblProducts[Cost Price])) -> 450 | H2: =IF(tblPurchases[[#This Row],[Product ID]] ="","",tblPurchases[[#This Row],[Cost Price]]*tblPurchases[[#This Row],[Qty Purchased]]) -> 22500
A3: PO002 | B3: 46024 | C3: Prime Office Supplies | D3: P006 | E3: =IF(tblPurchases[[#This Row],[Product ID]]="","",_xlfn.XLOOKUP(tblPurchases[[#This Row],[Product ID]],tblProducts[Product ID],tblProducts[Product Name])) -> Notebook A5 | F3: 100 | G3: =IF(tblPurchases[[#This Row],[Product ID]] ="","",_xlfn.XLOOKUP(tblPurchases[[#This Row],[Product]],tblProducts[Product Name],tblProducts[Cost Price])) -> 45 | H3: =IF(tblPurchases[[#This Row],[Product ID]] ="","",tblPurchases[[#This Row],[Cost Price]]*tblPurchases[[#This Row],[Qty Purchased]]) -> 4500
A4: PO003 | B4: 46025 | C4: Metro Traders | D4: P007 | E4: =IF(tblPurchases[[#This Row],[Product ID]]="","",_xlfn.XLOOKUP(tblPurchases[[#This Row],[Product ID]],tblProducts[Product ID],tblProducts[Product Name])) -> Ball Pen | F4: 200 | G4: =IF(tblPurchases[[#This Row],[Product ID]] ="","",_xlfn.XLOOKUP(tblPurchases[[#This Row],[Product]],tblProducts[Product Name],tblProducts[Cost Price])) -> 12 | H4: =IF(tblPurchases[[#This Row],[Product ID]] ="","",tblPurchases[[#This Row],[Cost Price]]*tblPurchases[[#This Row],[Qty Purchased]]) -> 2400
A5: PO004 | B5: 46026 | C5: Elite Electronics | D5: P005 | E5: =IF(tblPurchases[[#This Row],[Product ID]]="","",_xlfn.XLOOKUP(tblPurchases[[#This Row],[Product ID]],tblProducts[Product ID],tblProducts[Product Name])) -> HDMI Cable | F5: 75 | G5: =IF(tblPurchases[[#This Row],[Product ID]] ="","",_xlfn.XLOOKUP(tblPurchases[[#This Row],[Product]],tblProducts[Product Name],tblProducts[Cost Price])) -> 180 | H5: =IF(tblPurchases[[#This Row],[Product ID]] ="","",tblPurchases[[#This Row],[Cost Price]]*tblPurchases[[#This Row],[Qty Purchased]]) -> 13500
A6: PO005 | B6: 46027 | C6: Bright Stationers | D6: P009 | E6: =IF(tblPurchases[[#This Row],[Product ID]]="","",_xlfn.XLOOKUP(tblPurchases[[#This Row],[Product ID]],tblProducts[Product ID],tblProducts[Product Name])) -> Printer Paper (500 Sheets) | F6: 60 | G6: =IF(tblPurchases[[#This Row],[Product ID]] ="","",_xlfn.XLOOKUP(tblPurchases[[#This Row],[Product]],tblProducts[Product Name],tblProducts[Cost Price])) -> 220 | H6: =IF(tblPurchases[[#This Row],[Product ID]] ="","",tblPurchases[[#This Row],[Cost Price]]*tblPurchases[[#This Row],[Qty Purchased]]) -> 13200
A7: PO006 | B7: 46029 | C7: SmartTech Solutions | D7: P002 | E7: =IF(tblPurchases[[#This Row],[Product ID]]="","",_xlfn.XLOOKUP(tblPurchases[[#This Row],[Product ID]],tblProducts[Product ID],tblProducts[Product Name])) -> Wireless Keyboard | F7: 30 | G7: =IF(tblPurchases[[#This Row],[Product ID]] ="","",_xlfn.XLOOKUP(tblPurchases[[#This Row],[Product]],tblProducts[Product Name],tblProducts[Cost Price])) -> 900 | H7: =IF(tblPurchases[[#This Row],[Product ID]] ="","",tblPurchases[[#This Row],[Cost Price]]*tblPurchases[[#This Row],[Qty Purchased]]) -> 27000
A8: PO007 | B8: 46030 | C8: Urban Furniture Hub | D8: P011 | E8: =IF(tblPurchases[[#This Row],[Product ID]]="","",_xlfn.XLOOKUP(tblPurchases[[#This Row],[Product ID]],tblProducts[Product ID],tblProducts[Product Name])) -> Office Chair | F8: 10 | G8: =IF(tblPurchases[[#This Row],[Product ID]] ="","",_xlfn.XLOOKUP(tblPurchases[[#This Row],[Product]],tblProducts[Product Name],tblProducts[Cost Price])) -> 3500 | H8: =IF(tblPurchases[[#This Row],[Product ID]] ="","",tblPurchases[[#This Row],[Cost Price]]*tblPurchases[[#This Row],[Qty Purchased]]) -> 35000
A9: PO008 | B9: 46031 | C9: Galaxy Wholesale | D9: P017 | E9: =IF(tblPurchases[[#This Row],[Product ID]]="","",_xlfn.XLOOKUP(tblPurchases[[#This Row],[Product ID]],tblProducts[Product ID],tblProducts[Product Name])) -> Laptop Backpack | F9: 25 | G9: =IF(tblPurchases[[#This Row],[Product ID]] ="","",_xlfn.XLOOKUP(tblPurchases[[#This Row],[Product]],tblProducts[Product Name],tblProducts[Cost Price])) -> 850 | H9: =IF(tblPurchases[[#This Row],[Product ID]] ="","",tblPurchases[[#This Row],[Cost Price]]*tblPurchases[[#This Row],[Qty Purchased]]) -> 21250
A10: PO009 | B10: 46032 | C10: Zenith Business Supplies | D10: P020 | E10: =IF(tblPurchases[[#This Row],[Product ID]]="","",_xlfn.XLOOKUP(tblPurchases[[#This Row],[Product ID]],tblProducts[Product ID],tblProducts[Product Name])) -> Bluetooth Speaker | F10: 15 | G10: =IF(tblPurchases[[#This Row],[Product ID]] ="","",_xlfn.XLOOKUP(tblPurchases[[#This Row],[Product]],tblProducts[Product Name],tblProducts[Cost Price])) -> 1100 | H10: =IF(tblPurchases[[#This Row],[Product ID]] ="","",tblPurchases[[#This Row],[Cost Price]]*tblPurchases[[#This Row],[Qty Purchased]]) -> 16500
A11: PO010 | B11: 46033 | C11: TechSource India | D11: P003 | E11: =IF(tblPurchases[[#This Row],[Product ID]]="","",_xlfn.XLOOKUP(tblPurchases[[#This Row],[Product ID]],tblProducts[Product ID],tblProducts[Product Name])) -> USB Flash Drive 32GB | F11: 80 | G11: =IF(tblPurchases[[#This Row],[Product ID]] ="","",_xlfn.XLOOKUP(tblPurchases[[#This Row],[Product]],tblProducts[Product Name],tblProducts[Cost Price])) -> 350 | H11: =IF(tblPurchases[[#This Row],[Product ID]] ="","",tblPurchases[[#This Row],[Cost Price]]*tblPurchases[[#This Row],[Qty Purchased]]) -> 28000
A12: PO011 | B12: 46035 | C12: Prime Office Supplies | D12: P022 | E12: =IF(tblPurchases[[#This Row],[Product ID]]="","",_xlfn.XLOOKUP(tblPurchases[[#This Row],[Product ID]],tblProducts[Product ID],tblProducts[Product Name])) -> Calculator | F12: 35 | G12: =IF(tblPurchases[[#This Row],[Product ID]] ="","",_xlfn.XLOOKUP(tblPurchases[[#This Row],[Product]],tblProducts[Product Name],tblProducts[Cost Price])) -> 350 | H12: =IF(tblPurchases[[#This Row],[Product ID]] ="","",tblPurchases[[#This Row],[Cost Price]]*tblPurchases[[#This Row],[Qty Purchased]]) -> 12250
A13: PO012 | B13: 46037 | C13: Metro Traders | D13: P024 | E13: =IF(tblPurchases[[#This Row],[Product ID]]="","",_xlfn.XLOOKUP(tblPurchases[[#This Row],[Product ID]],tblProducts[Product ID],tblProducts[Product Name])) -> File Folder | F13: 150 | G13: =IF(tblPurchases[[#This Row],[Product ID]] ="","",_xlfn.XLOOKUP(tblPurchases[[#This Row],[Product]],tblProducts[Product Name],tblProducts[Cost Price])) -> 18 | H13: =IF(tblPurchases[[#This Row],[Product ID]] ="","",tblPurchases[[#This Row],[Cost Price]]*tblPurchases[[#This Row],[Qty Purchased]]) -> 2700
... A61: PO060 | B61: 46138 | C61: SmartTech Solutions | D61: P007 | E61: =IF(tblPurchases[[#This Row],[Product ID]]="","",_xlfn.XLOOKUP(tblPurchases[[#This Row],[Product ID]],tblProducts[Product ID],tblProducts[Product Name])) -> Ball Pen | F61: 180 | G61: =IF(tblPurchases[[#This Row],[Product ID]] ="","",_xlfn.XLOOKUP(tblPurchases[[#This Row],[Product]],tblProducts[Product Name],tblProducts[Cost Price])) -> 12 | H61: =IF(tblPurchases[[#This Row],[Product ID]] ="","",tblPurchases[[#This Row],[Cost Price]]*tblPurchases[[#This Row],[Qty Purchased]]) -> 2160

Sheet Sales
A1: Invoice No | B1: Date | C1: Customer | D1: Product ID | E1: Product Name | F1: Qty Sold | G1: Selling Price | H1: Total Sales
A2: INV001 | B2: 46027 | C2: Apex Retail | D2: P001 | E2: =IF(tblSales[[#This Row],[Product ID]]="","",(_xlfn.XLOOKUP(tblSales[[#This Row],[Product ID]],tblProducts[Product ID],tblProducts[Product Name]))) -> Wireless Mouse | F2: 15 | G2: =IF(tblSales[[#This Row],[Product ID]]="","",_xlfn.XLOOKUP(tblSales[[#This Row],[Product ID]],tblProducts[Product ID],tblProducts[Selling Price])) -> 650 | H2: =IF(tblSales[[#This Row],[Product ID]]="","",tblSales[[#This Row],[Selling Price]]*tblSales[[#This Row],[Qty Sold]]) -> 9750
A3: INV002 | B3: 46028 | C3: Bright Stores | D3: P006 | E3: =IF(tblSales[[#This Row],[Product ID]]="","",(_xlfn.XLOOKUP(tblSales[[#This Row],[Product ID]],tblProducts[Product ID],tblProducts[Product Name]))) -> Notebook A5 | F3: 40 | G3: =IF(tblSales[[#This Row],[Product ID]]="","",_xlfn.XLOOKUP(tblSales[[#This Row],[Product ID]],tblProducts[Product ID],tblProducts[Selling Price])) -> 80 | H3: =IF(tblSales[[#This Row],[Product ID]]="","",tblSales[[#This Row],[Selling Price]]*tblSales[[#This Row],[Qty Sold]]) -> 3200
A4: INV003 | B4: 46029 | C4: City Mart | D4: P007 | E4: =IF(tblSales[[#This Row],[Product ID]]="","",(_xlfn.XLOOKUP(tblSales[[#This Row],[Product ID]],tblProducts[Product ID],tblProducts[Product Name]))) -> Ball Pen | F4: 70 | G4: =IF(tblSales[[#This Row],[Product ID]]="","",_xlfn.XLOOKUP(tblSales[[#This Row],[Product ID]],tblProducts[Product ID],tblProducts[Selling Price])) -> 25 | H4: =IF(tblSales[[#This Row],[Product ID]]="","",tblSales[[#This Row],[Selling Price]]*tblSales[[#This Row],[Qty Sold]]) -> 1750
A5: INV004 | B5: 46030 | C5: Elite Traders | D5: P005 | E5: =IF(tblSales[[#This Row],[Product ID]]="","",(_xlfn.XLOOKUP(tblSales[[#This Row],[Product ID]],tblProducts[Product ID],tblProducts[Product Name]))) -> HDMI Cable | F5: 20 | G5: =IF(tblSales[[#This Row],[Product ID]]="","",_xlfn.XLOOKUP(tblSales[[#This Row],[Product ID]],tblProducts[Product ID],tblProducts[Selling Price])) -> 350 | H5: =IF(tblSales[[#This Row],[Product ID]]="","",tblSales[[#This Row],[Selling Price]]*tblSales[[#This Row],[Qty Sold]]) -> 7000
A6: INV005 | B6: 46031 | C6: Future Electronics | D6: P002 | E6: =IF(tblSales[[#This Row],[Product ID]]="","",(_xlfn.XLOOKUP(tblSales[[#This Row],[Product ID]],tblProducts[Product ID],tblProducts[Product Name]))) -> Wireless Keyboard | F6: 10 | G6: =IF(tblSales[[#This Row],[Product ID]]="","",_xlfn.XLOOKUP(tblSales[[#This Row],[Product ID]],tblProducts[Product ID],tblProducts[Selling Price])) -> 1300 | H6: =IF(tblSales[[#This Row],[Product ID]]="","",tblSales[[#This Row],[Selling Price]]*tblSales[[#This Row],[Qty Sold]]) -> 13000
A7: INV006 | B7: 46032 | C7: Global Supplies | D7: P003 | E7: =IF(tblSales[[#This Row],[Product ID]]="","",(_xlfn.XLOOKUP(tblSales[[#This Row],[Product ID]],tblProducts[Product ID],tblProducts[Product Name]))) -> USB Flash Drive 32GB | F7: 25 | G7: =IF(tblSales[[#This Row],[Product ID]]="","",_xlfn.XLOOKUP(tblSales[[#This Row],[Product ID]],tblProducts[Product ID],tblProducts[Selling Price])) -> 550 | H7: =IF(tblSales[[#This Row],[Product ID]]="","",tblSales[[#This Row],[Selling Price]]*tblSales[[#This Row],[Qty Sold]]) -> 13750
A8: INV007 | B8: 46033 | C8: Metro Bazaar | D8: P011 | E8: =IF(tblSales[[#This Row],[Product ID]]="","",(_xlfn.XLOOKUP(tblSales[[#This Row],[Product ID]],tblProducts[Product ID],tblProducts[Product Name]))) -> Office Chair | F8: 3 | G8: =IF(tblSales[[#This Row],[Product ID]]="","",_xlfn.XLOOKUP(tblSales[[#This Row],[Product ID]],tblProducts[Product ID],tblProducts[Selling Price])) -> 5000 | H8: =IF(tblSales[[#This Row],[Product ID]]="","",tblSales[[#This Row],[Selling Price]]*tblSales[[#This Row],[Qty Sold]]) -> 15000
A9: INV008 | B9: 46034 | C9: Nova Enterprises | D9: P017 | E9: =IF(tblSales[[#This Row],[Product ID]]="","",(_xlfn.XLOOKUP(tblSales[[#This Row],[Product ID]],tblProducts[Product ID],tblProducts[Product Name]))) -> Laptop Backpack | F9: 8 | G9: =IF(tblSales[[#This Row],[Product ID]]="","",_xlfn.XLOOKUP(tblSales[[#This Row],[Product ID]],tblProducts[Product ID],tblProducts[Selling Price])) -> 1300 | H9: =IF(tblSales[[#This Row],[Product ID]]="","",tblSales[[#This Row],[Selling Price]]*tblSales[[#This Row],[Qty Sold]]) -> 10400
A10: INV009 | B10: 46035 | C10: Prime Retailers | D10: P020 | E10: =IF(tblSales[[#This Row],[Product ID]]="","",(_xlfn.XLOOKUP(tblSales[[#This Row],[Product ID]],tblProducts[Product ID],tblProducts[Product Name]))) -> Bluetooth Speaker | F10: 5 | G10: =IF(tblSales[[#This Row],[Product ID]]="","",_xlfn.XLOOKUP(tblSales[[#This Row],[Product ID]],tblProducts[Product ID],tblProducts[Selling Price])) -> 1700 | H10: =IF(tblSales[[#This Row],[Product ID]]="","",tblSales[[#This Row],[Selling Price]]*tblSales[[#This Row],[Qty Sold]]) -> 8500
A11: INV010 | B11: 46037 | C11: Sunrise Distributors | D11: P016 | E11: =IF(tblSales[[#This Row],[Product ID]]="","",(_xlfn.XLOOKUP(tblSales[[#This Row],[Product ID]],tblProducts[Product ID],tblProducts[Product Name]))) -> Water Bottle 1L | F11: 30 | G11: =IF(tblSales[[#This Row],[Product ID]]="","",_xlfn.XLOOKUP(tblSales[[#This Row],[Product ID]],tblProducts[Product ID],tblProducts[Selling Price])) -> 220 | H11: =IF(tblSales[[#This Row],[Product ID]]="","",tblSales[[#This Row],[Selling Price]]*tblSales[[#This Row],[Qty Sold]]) -> 6600
A12: INV011 | B12: 46039 | C12: Apex Retail | D12: P023 | E12: =IF(tblSales[[#This Row],[Product ID]]="","",(_xlfn.XLOOKUP(tblSales[[#This Row],[Product ID]],tblProducts[Product ID],tblProducts[Product Name]))) -> Extension Board | F12: 15 | G12: =IF(tblSales[[#This Row],[Product ID]]="","",_xlfn.XLOOKUP(tblSales[[#This Row],[Product ID]],tblProducts[Product ID],tblProducts[Selling Price])) -> 450 | H12: =IF(tblSales[[#This Row],[Product ID]]="","",tblSales[[#This Row],[Selling Price]]*tblSales[[#This Row],[Qty Sold]]) -> 6750
A13: INV012 | B13: 46040 | C13: Bright Stores | D13: P021 | E13: =IF(tblSales[[#This Row],[Product ID]]="","",(_xlfn.XLOOKUP(tblSales[[#This Row],[Product ID]],tblProducts[Product ID],tblProducts[Product Name]))) -> Whiteboard Marker | F13: 60 | G13: =IF(tblSales[[#This Row],[Product ID]]="","",_xlfn.XLOOKUP(tblSales[[#This Row],[Product ID]],tblProducts[Product ID],tblProducts[Selling Price])) -> 55 | H13: =IF(tblSales[[#This Row],[Product ID]]="","",tblSales[[#This Row],[Selling Price]]*tblSales[[#This Row],[Qty Sold]]) -> 3300
... A121: INV120 | B121: 46168 | C121: Sunrise Distributors | D121: P017 | E121: =IF(tblSales[[#This Row],[Product ID]]="","",(_xlfn.XLOOKUP(tblSales[[#This Row],[Product ID]],tblProducts[Product ID],tblProducts[Product Name]))) -> Laptop Backpack | F121: 9 | G121: =IF(tblSales[[#This Row],[Product ID]]="","",_xlfn.XLOOKUP(tblSales[[#This Row],[Product ID]],tblProducts[Product ID],tblProducts[Selling Price])) -> 1300 | H121: =IF(tblSales[[#This Row],[Product ID]]="","",tblSales[[#This Row],[Selling Price]]*tblSales[[#This Row],[Qty Sold]]) -> 11700

Sheet Inventory Report
A1: Product ID | B1: Product Name | C1: Category | D1: Opening Stock | E1: Purchased Qty | F1: Sold Qty | G1: Cost Value | H1: Sales Value | I1: Current Stock | J1: Inventory Value | K1: Stock Status
A2: =tblProducts[[#This Row],[Product ID]] -> P001 | B2: =tblProducts[[#This Row],[Product Name]] -> Wireless Mouse | C2: =_xlfn.XLOOKUP(tblInventoryReport[[#This Row],[Product ID]],tblProducts[Product ID],tblProducts[Category]) -> Electronics | D2: =_xlfn.XLOOKUP(tblInventoryReport[[#This Row],[Product ID]],tblProducts[Product ID],tblProducts[Opening Stock]) -> 100 | E2: =SUMIFS(tblPurchases[Qty Purchased],tblPurchases[Product ID],tblInventoryReport[[#This Row],[Product ID]]) -> 180 | F2: =SUMIFS(tblSales[Qty Sold],tblSales[Product ID],tblInventoryReport[[#This Row],[Product ID]]) -> 127 | G2: =_xlfn.XLOOKUP(tblInventoryReport[[#This Row],[Product ID]],tblProducts[Product ID],tblProducts[Cost Price]) -> 450 | H2: =_xlfn.XLOOKUP(tblInventoryReport[[#This Row],[Product ID]],tblProducts[Product ID],tblProducts[Selling Price]) -> 650 | I2: =tblInventoryReport[[#This Row],[Opening Stock]]+tblInventoryReport[[#This Row],[Purchased Qty]]-tblInventoryReport[[#This Row],[Sold Qty]] -> 153 | J2: =tblInventoryReport[[#This Row],[Current Stock]]*tblInventoryReport[[#This Row],[Cost Value]] -> 68850 | K2: =IF(tblInventoryReport[[#This Row],[Current Stock]] = 0,"Out of Stock",IF(tblInventoryReport[[#This Row],[Current Stock]]<=_xlfn.XLOOKUP(tblInventoryReport[[#This Row],[Product ID]],tblProducts[Product ID],tblProducts[Reorder Level]),"Low Stock", "In Stock")) -> In Stock
A3: =tblProducts[[#This Row],[Product ID]] -> P002 | B3: =tblProducts[[#This Row],[Product Name]] -> Wireless Keyboard | C3: =_xlfn.XLOOKUP(tblInventoryReport[[#This Row],[Product ID]],tblProducts[Product ID],tblProducts[Category]) -> Electronics | D3: =_xlfn.XLOOKUP(tblInventoryReport[[#This Row],[Product ID]],tblProducts[Product ID],tblProducts[Opening Stock]) -> 80 | E3: =SUMIFS(tblPurchases[Qty Purchased],tblPurchases[Product ID],tblInventoryReport[[#This Row],[Product ID]]) -> 55 | F3: =SUMIFS(tblSales[Qty Sold],tblSales[Product ID],tblInventoryReport[[#This Row],[Product ID]]) -> 25 | G3: =_xlfn.XLOOKUP(tblInventoryReport[[#This Row],[Product ID]],tblProducts[Product ID],tblProducts[Cost Price]) -> 900 | H3: =_xlfn.XLOOKUP(tblInventoryReport[[#This Row],[Product ID]],tblProducts[Product ID],tblProducts[Selling Price]) -> 1300 | I3: =tblInventoryReport[[#This Row],[Opening Stock]]+tblInventoryReport[[#This Row],[Purchased Qty]]-tblInventoryReport[[#This Row],[Sold Qty]] -> 110 | J3: =tblInventoryReport[[#This Row],[Current Stock]]*tblInventoryReport[[#This Row],[Cost Value]] -> 99000 | K3: =IF(tblInventoryReport[[#This Row],[Current Stock]] = 0,"Out of Stock",IF(tblInventoryReport[[#This Row],[Current Stock]]<=_xlfn.XLOOKUP(tblInventoryReport[[#This Row],[Product ID]],tblProducts[Product ID],tblProducts[Reorder Level]),"Low Stock", "In Stock")) -> In Stock
A4: =tblProducts[[#This Row],[Product ID]] -> P003 | B4: =tblProducts[[#This Row],[Product Name]] -> USB Flash Drive 32GB | C4: =_xlfn.XLOOKUP(tblInventoryReport[[#This Row],[Product ID]],tblProducts[Product ID],tblProducts[Category]) -> Electronics | D4: =_xlfn.XLOOKUP(tblInventoryReport[[#This Row],[Product ID]],tblProducts[Product ID],tblProducts[Opening Stock]) -> 120 | E4: =SUMIFS(tblPurchases[Qty Purchased],tblPurchases[Product ID],tblInventoryReport[[#This Row],[Product ID]]) -> 210 | F4: =SUMIFS(tblSales[Qty Sold],tblSales[Product ID],tblInventoryReport[[#This Row],[Product ID]]) -> 125 | G4: =_xlfn.XLOOKUP(tblInventoryReport[[#This Row],[Product ID]],tblProducts[Product ID],tblProducts[Cost Price]) -> 350 | H4: =_xlfn.XLOOKUP(tblInventoryReport[[#This Row],[Product ID]],tblProducts[Product ID],tblProducts[Selling Price]) -> 550 | I4: =tblInventoryReport[[#This Row],[Opening Stock]]+tblInventoryReport[[#This Row],[Purchased Qty]]-tblInventoryReport[[#This Row],[Sold Qty]] -> 205 | J4: =tblInventoryReport[[#This Row],[Current Stock]]*tblInventoryReport[[#This Row],[Cost Value]] -> 71750 | K4: =IF(tblInventoryReport[[#This Row],[Current Stock]] = 0,"Out of Stock",IF(tblInventoryReport[[#This Row],[Current Stock]]<=_xlfn.XLOOKUP(tblInventoryReport[[#This Row],[Product ID]],tblProducts[Product ID],tblProducts[Reorder Level]),"Low Stock", "In Stock")) -> In Stock
A5: =tblProducts[[#This Row],[Product ID]] -> P004 | B5: =tblProducts[[#This Row],[Product Name]] -> External Hard Drive 1TB | C5: =_xlfn.XLOOKUP(tblInventoryReport[[#This Row],[Product ID]],tblProducts[Product ID],tblProducts[Category]) -> Electronics | D5: =_xlfn.XLOOKUP(tblInventoryReport[[#This Row],[Product ID]],tblProducts[Product ID],tblProducts[Opening Stock]) -> 40 | E5: =SUMIFS(tblPurchases[Qty Purchased],tblPurchases[Product ID],tblInventoryReport[[#This Row],[Product ID]]) -> 22 | F5: =SUMIFS(tblSales[Qty Sold],tblSales[Product ID],tblInventoryReport[[#This Row],[Product ID]]) -> 9 | G5: =_xlfn.XLOOKUP(tblInventoryReport[[#This Row],[Product ID]],tblProducts[Product ID],tblProducts[Cost Price]) -> 3200 | H5: =_xlfn.XLOOKUP(tblInventoryReport[[#This Row],[Product ID]],tblProducts[Product ID],tblProducts[Selling Price]) -> 4200 | I5: =tblInventoryReport[[#This Row],[Opening Stock]]+tblInventoryReport[[#This Row],[Purchased Qty]]-tblInventoryReport[[#This Row],[Sold Qty]] -> 53 | J5: =tblInventoryReport[[#This Row],[Current Stock]]*tblInventoryReport[[#This Row],[Cost Value]] -> 169600 | K5: =IF(tblInventoryReport[[#This Row],[Current Stock]] = 0,"Out of Stock",IF(tblInventoryReport[[#This Row],[Current Stock]]<=_xlfn.XLOOKUP(tblInventoryReport[[#This Row],[Product ID]],tblProducts[Product ID],tblProducts[Reorder Level]),"Low Stock", "In Stock")) -> In Stock
A6: =tblProducts[[#This Row],[Product ID]] -> P005 | B6: =tblProducts[[#This Row],[Product Name]] -> HDMI Cable | C6: =_xlfn.XLOOKUP(tblInventoryReport[[#This Row],[Product ID]],tblProducts[Product ID],tblProducts[Category]) -> Electronics | D6: =_xlfn.XLOOKUP(tblInventoryReport[[#This Row],[Product ID]],tblProducts[Product ID],tblProducts[Opening Stock]) -> 150 | E6: =SUMIFS(tblPurchases[Qty Purchased],tblPurchases[Product ID],tblInventoryReport[[#This Row],[Product ID]]) -> 190 | F6: =SUMIFS(tblSales[Qty Sold],tblSales[Product ID],tblInventoryReport[[#This Row],[Product ID]]) -> 129 | G6: =_xlfn.XLOOKUP(tblInventoryReport[[#This Row],[Product ID]],tblProducts[Product ID],tblProducts[Cost Price]) -> 180 | H6: =_xlfn.XLOOKUP(tblInventoryReport[[#This Row],[Product ID]],tblProducts[Product ID],tblProducts[Selling Price]) -> 350 | I6: =tblInventoryReport[[#This Row],[Opening Stock]]+tblInventoryReport[[#This Row],[Purchased Qty]]-tblInventoryReport[[#This Row],[Sold Qty]] -> 211 | J6: =tblInventoryReport[[#This Row],[Current Stock]]*tblInventoryReport[[#This Row],[Cost Value]] -> 37980 | K6: =IF(tblInventoryReport[[#This Row],[Current Stock]] = 0,"Out of Stock",IF(tblInventoryReport[[#This Row],[Current Stock]]<=_xlfn.XLOOKUP(tblInventoryReport[[#This Row],[Product ID]],tblProducts[Product ID],tblProducts[Reorder Level]),"Low Stock", "In Stock")) -> In Stock
A7: =tblProducts[[#This Row],[Product ID]] -> P006 | B7: =tblProducts[[#This Row],[Product Name]] -> Notebook A5 | C7: =_xlfn.XLOOKUP(tblInventoryReport[[#This Row],[Product ID]],tblProducts[Product ID],tblProducts[Category]) -> Stationery | D7: =_xlfn.XLOOKUP(tblInventoryReport[[#This Row],[Product ID]],tblProducts[Product ID],tblProducts[Opening Stock]) -> 300 | E7: =SUMIFS(tblPurchases[Qty Purchased],tblPurchases[Product ID],tblInventoryReport[[#This Row],[Product ID]]) -> 270 | F7: =SUMIFS(tblSales[Qty Sold],tblSales[Product ID],tblInventoryReport[[#This Row],[Product ID]]) -> 208 | G7: =_xlfn.XLOOKUP(tblInventoryReport[[#This Row],[Product ID]],tblProducts[Product ID],tblProducts[Cost Price]) -> 45 | H7: =_xlfn.XLOOKUP(tblInventoryReport[[#This Row],[Product ID]],tblProducts[Product ID],tblProducts[Selling Price]) -> 80 | I7: =tblInventoryReport[[#This Row],[Opening Stock]]+tblInventoryReport[[#This Row],[Purchased Qty]]-tblInventoryReport[[#This Row],[Sold Qty]] -> 362 | J7: =tblInventoryReport[[#This Row],[Current Stock]]*tblInventoryReport[[#This Row],[Cost Value]] -> 16290 | K7: =IF(tblInventoryReport[[#This Row],[Current Stock]] = 0,"Out of Stock",IF(tblInventoryReport[[#This Row],[Current Stock]]<=_xlfn.XLOOKUP(tblInventoryReport[[#This Row],[Product ID]],tblProducts[Product ID],tblProducts[Reorder Level]),"Low Stock", "In Stock")) -> In Stock
A8: =tblProducts[[#This Row],[Product ID]] -> P007 | B8: =tblProducts[[#This Row],[Product Name]] -> Ball Pen | C8: =_xlfn.XLOOKUP(tblInventoryReport[[#This Row],[Product ID]],tblProducts[Product ID],tblProducts[Category]) -> Stationery | D8: =_xlfn.XLOOKUP(tblInventoryReport[[#This Row],[Product ID]],tblProducts[Product ID],tblProducts[Opening Stock]) -> 500 | E8: =SUMIFS(tblPurchases[Qty Purchased],tblPurchases[Product ID],tblInventoryReport[[#This Row],[Product ID]]) -> 780 | F8: =SUMIFS(tblSales[Qty Sold],tblSales[Product ID],tblInventoryReport[[#This Row],[Product ID]]) -> 520 | G8: =_xlfn.XLOOKUP(tblInventoryReport[[#This Row],[Product ID]],tblProducts[Product ID],tblProducts[Cost Price]) -> 12 | H8: =_xlfn.XLOOKUP(tblInventoryReport[[#This Row],[Product ID]],tblProducts[Product ID],tblProducts[Selling Price]) -> 25 | I8: =tblInventoryReport[[#This Row],[Opening Stock]]+tblInventoryReport[[#This Row],[Purchased Qty]]-tblInventoryReport[[#This Row],[Sold Qty]] -> 760 | J8: =tblInventoryReport[[#This Row],[Current Stock]]*tblInventoryReport[[#This Row],[Cost Value]] -> 9120 | K8: =IF(tblInventoryReport[[#This Row],[Current Stock]] = 0,"Out of Stock",IF(tblInventoryReport[[#This Row],[Current Stock]]<=_xlfn.XLOOKUP(tblInventoryReport[[#This Row],[Product ID]],tblProducts[Product ID],tblProducts[Reorder Level]),"Low Stock", "In Stock")) -> In Stock
A9: =tblProducts[[#This Row],[Product ID]] -> P008 | B9: =tblProducts[[#This Row],[Product Name]] -> Stapler | C9: =_xlfn.XLOOKUP(tblInventoryReport[[#This Row],[Product ID]],tblProducts[Product ID],tblProducts[Category]) -> Stationery | D9: =_xlfn.XLOOKUP(tblInventoryReport[[#This Row],[Product ID]],tblProducts[Product ID],tblProducts[Opening Stock]) -> 90 | E9: =SUMIFS(tblPurchases[Qty Purchased],tblPurchases[Product ID],tblInventoryReport[[#This Row],[Product ID]]) -> 85 | F9: =SUMIFS(tblSales[Qty Sold],tblSales[Product ID],tblInventoryReport[[#This Row],[Product ID]]) -> 43 | G9: =_xlfn.XLOOKUP(tblInventoryReport[[#This Row],[Product ID]],tblProducts[Product ID],tblProducts[Cost Price]) -> 110 | H9: =_xlfn.XLOOKUP(tblInventoryReport[[#This Row],[Product ID]],tblProducts[Product ID],tblProducts[Selling Price]) -> 180 | I9: =tblInventoryReport[[#This Row],[Opening Stock]]+tblInventoryReport[[#This Row],[Purchased Qty]]-tblInventoryReport[[#This Row],[Sold Qty]] -> 132 | J9: =tblInventoryReport[[#This Row],[Current Stock]]*tblInventoryReport[[#This Row],[Cost Value]] -> 14520 | K9: =IF(tblInventoryReport[[#This Row],[Current Stock]] = 0,"Out of Stock",IF(tblInventoryReport[[#This Row],[Current Stock]]<=_xlfn.XLOOKUP(tblInventoryReport[[#This Row],[Product ID]],tblProducts[Product ID],tblProducts[Reorder Level]),"Low Stock", "In Stock")) -> In Stock
A10: =tblProducts[[#This Row],[Product ID]] -> P009 | B10: =tblProducts[[#This Row],[Product Name]] -> Printer Paper (500 Sheets) | C10: =_xlfn.XLOOKUP(tblInventoryReport[[#This Row],[Product ID]],tblProducts[Product ID],tblProducts[Category]) -> Stationery | D10: =_xlfn.XLOOKUP(tblInventoryReport[[#This Row],[Product ID]],tblProducts[Product ID],tblProducts[Opening Stock]) -> 100 | E10: =SUMIFS(tblPurchases[Qty Purchased],tblPurchases[Product ID],tblInventoryReport[[#This Row],[Product ID]]) -> 180 | F10: =SUMIFS(tblSales[Qty Sold],tblSales[Product ID],tblInventoryReport[[#This Row],[Product ID]]) -> 111 | G10: =_xlfn.XLOOKUP(tblInventoryReport[[#This Row],[Product ID]],tblProducts[Product ID],tblProducts[Cost Price]) -> 220 | H10: =_xlfn.XLOOKUP(tblInventoryReport[[#This Row],[Product ID]],tblProducts[Product ID],tblProducts[Selling Price]) -> 320 | I10: =tblInventoryReport[[#This Row],[Opening Stock]]+tblInventoryReport[[#This Row],[Purchased Qty]]-tblInventoryReport[[#This Row],[Sold Qty]] -> 169 | J10: =tblInventoryReport[[#This Row],[Current Stock]]*tblInventoryReport[[#This Row],[Cost Value]] -> 37180 | K10: =IF(tblInventoryReport[[#This Row],[Current Stock]] = 0,"Out of Stock",IF(tblInventoryReport[[#This Row],[Current Stock]]<=_xlfn.XLOOKUP(tblInventoryReport[[#This Row],[Product ID]],tblProducts[Product ID],tblProducts[Reorder Level]),"Low Stock", "In Stock")) -> In Stock
A11: =tblProducts[[#This Row],[Product ID]] -> P010 | B11: =tblProducts[[#This Row],[Product Name]] -> Highlighter Set | C11: =_xlfn.XLOOKUP(tblInventoryReport[[#This Row],[Product ID]],tblProducts[Product ID],tblProducts[Category]) -> Stationery | D11: =_xlfn.XLOOKUP(tblInventoryReport[[#This Row],[Product ID]],tblProducts[Product ID],tblProducts[Opening Stock]) -> 75 | E11: =SUMIFS(tblPurchases[Qty Purchased],tblPurchases[Product ID],tblInventoryReport[[#This Row],[Product ID]]) -> 90 | F11: =SUMIFS(tblSales[Qty Sold],tblSales[Product ID],tblInventoryReport[[#This Row],[Product ID]]) -> 56 | G11: =_xlfn.XLOOKUP(tblInventoryReport[[#This Row],[Product ID]],tblProducts[Product ID],tblProducts[Cost Price]) -> 95 | H11: =_xlfn.XLOOKUP(tblInventoryReport[[#This Row],[Product ID]],tblProducts[Product ID],tblProducts[Selling Price]) -> 160 | I11: =tblInventoryReport[[#This Row],[Opening Stock]]+tblInventoryReport[[#This Row],[Purchased Qty]]-tblInventoryReport[[#This Row],[Sold Qty]] -> 109 | J11: =tblInventoryReport[[#This Row],[Current Stock]]*tblInventoryReport[[#This Row],[Cost Value]] -> 10355 | K11: =IF(tblInventoryReport[[#This Row],[Current Stock]] = 0,"Out of Stock",IF(tblInventoryReport[[#This Row],[Current Stock]]<=_xlfn.XLOOKUP(tblInventoryReport[[#This Row],[Product ID]],tblProducts[Product ID],tblProducts[Reorder Level]),"Low Stock", "In Stock")) -> In Stock
A12: =tblProducts[[#This Row],[Product ID]] -> P011 | B12: =tblProducts[[#This Row],[Product Name]] -> Office Chair | C12: =_xlfn.XLOOKUP(tblInventoryReport[[#This Row],[Product ID]],tblProducts[Product ID],tblProducts[Category]) -> Furniture | D12: =_xlfn.XLOOKUP(tblInventoryReport[[#This Row],[Product ID]],tblProducts[Product ID],tblProducts[Opening Stock]) -> 25 | E12: =SUMIFS(tblPurchases[Qty Purchased],tblPurchases[Product ID],tblInventoryReport[[#This Row],[Product ID]]) -> 18 | F12: =SUMIFS(tblSales[Qty Sold],tblSales[Product ID],tblInventoryReport[[#This Row],[Product ID]]) -> 9 | G12: =_xlfn.XLOOKUP(tblInventoryReport[[#This Row],[Product ID]],tblProducts[Product ID],tblProducts[Cost Price]) -> 3500 | H12: =_xlfn.XLOOKUP(tblInventoryReport[[#This Row],[Product ID]],tblProducts[Product ID],tblProducts[Selling Price]) -> 5000 | I12: =tblInventoryReport[[#This Row],[Opening Stock]]+tblInventoryReport[[#This Row],[Purchased Qty]]-tblInventoryReport[[#This Row],[Sold Qty]] -> 34 | J12: =tblInventoryReport[[#This Row],[Current Stock]]*tblInventoryReport[[#This Row],[Cost Value]] -> 119000 | K12: =IF(tblInventoryReport[[#This Row],[Current Stock]] = 0,"Out of Stock",IF(tblInventoryReport[[#This Row],[Current Stock]]<=_xlfn.XLOOKUP(tblInventoryReport[[#This Row],[Product ID]],tblProducts[Product ID],tblProducts[Reorder Level]),"Low Stock", "In Stock")) -> In Stock
A13: =tblProducts[[#This Row],[Product ID]] -> P012 | B13: =tblProducts[[#This Row],[Product Name]] -> Study Table | C13: =_xlfn.XLOOKUP(tblInventoryReport[[#This Row],[Product ID]],tblProducts[Product ID],tblProducts[Category]) -> Furniture | D13: =_xlfn.XLOOKUP(tblInventoryReport[[#This Row],[Product ID]],tblProducts[Product ID],tblProducts[Opening Stock]) -> 18 | E13: =SUMIFS(tblPurchases[Qty Purchased],tblPurchases[Product ID],tblInventoryReport[[#This Row],[Product ID]]) -> 15 | F13: =SUMIFS(tblSales[Qty Sold],tblSales[Product ID],tblInventoryReport[[#This Row],[Product ID]]) -> 7 | G13: =_xlfn.XLOOKUP(tblInventoryReport[[#This Row],[Product ID]],tblProducts[Product ID],tblProducts[Cost Price]) -> 4200 | H13: =_xlfn.XLOOKUP(tblInventoryReport[[#This Row],[Product ID]],tblProducts[Product ID],tblProducts[Selling Price]) -> 6200 | I13: =tblInventoryReport[[#This Row],[Opening Stock]]+tblInventoryReport[[#This Row],[Purchased Qty]]-tblInventoryReport[[#This Row],[Sold Qty]] -> 26 | J13: =tblInventoryReport[[#This Row],[Current Stock]]*tblInventoryReport[[#This Row],[Cost Value]] -> 109200 | K13: =IF(tblInventoryReport[[#This Row],[Current Stock]] = 0,"Out of Stock",IF(tblInventoryReport[[#This Row],[Current Stock]]<=_xlfn.XLOOKUP(tblInventoryReport[[#This Row],[Product ID]],tblProducts[Product ID],tblProducts[Reorder Level]),"Low Stock", "In Stock")) -> In Stock
... A26: =tblProducts[[#This Row],[Product ID]] -> P025 | B26: =tblProducts[[#This Row],[Product Name]] -> Desk Organizer | C26: =_xlfn.XLOOKUP(tblInventoryReport[[#This Row],[Product ID]],tblProducts[Product ID],tblProducts[Category]) -> Accessories | D26: =_xlfn.XLOOKUP(tblInventoryReport[[#This Row],[Product ID]],tblProducts[Product ID],tblProducts[Opening Stock]) -> 85 | E26: =SUMIFS(tblPurchases[Qty Purchased],tblPurchases[Product ID],tblInventoryReport[[#This Row],[Product ID]]) -> 75 | F26: =SUMIFS(tblSales[Qty Sold],tblSales[Product ID],tblInventoryReport[[#This Row],[Product ID]]) -> 56 | G26: =_xlfn.XLOOKUP(tblInventoryReport[[#This Row],[Product ID]],tblProducts[Product ID],tblProducts[Cost Price]) -> 220 | H26: =_xlfn.XLOOKUP(tblInventoryReport[[#This Row],[Product ID]],tblProducts[Product ID],tblProducts[Selling Price]) -> 380 | I26: =tblInventoryReport[[#This Row],[Opening Stock]]+tblInventoryReport[[#This Row],[Purchased Qty]]-tblInventoryReport[[#This Row],[Sold Qty]] -> 104 | J26: =tblInventoryReport[[#This Row],[Current Stock]]*tblInventoryReport[[#This Row],[Cost Value]] -> 22880 | K26: =IF(tblInventoryReport[[#This Row],[Current Stock]] = 0,"Out of Stock",IF(tblInventoryReport[[#This Row],[Current Stock]]<=_xlfn.XLOOKUP(tblInventoryReport[[#This Row],[Product ID]],tblProducts[Product ID],tblProducts[Reorder Level]),"Low Stock", "In Stock")) -> In Stock
I28: =SUM(I2:I27) -> 3643

Sheet Products
A1: Product ID | B1: Product Name | C1: Category | D1: Unit | E1: Cost Price | F1: Selling Price | G1: Reorder Level | H1: Opening Stock
A2: P001 | B2: Wireless Mouse | C2: Electronics | D2: Piece | E2: 450 | F2: 650 | G2: 20 | H2: 100
A3: P002 | B3: Wireless Keyboard | C3: Electronics | D3: Piece | E3: 900 | F3: 1300 | G3: 15 | H3: 80
A4: P003 | B4: USB Flash Drive 32GB | C4: Electronics | D4: Piece | E4: 350 | F4: 550 | G4: 30 | H4: 120
A5: P004 | B5: External Hard Drive 1TB | C5: Electronics | D5: Piece | E5: 3200 | F5: 4200 | G5: 10 | H5: 40
A6: P005 | B6: HDMI Cable | C6: Electronics | D6: Piece | E6: 180 | F6: 350 | G6: 25 | H6: 150
A7: P006 | B7: Notebook A5 | C7: Stationery | D7: Piece | E7: 45 | F7: 80 | G7: 50 | H7: 300
A8: P007 | B8: Ball Pen | C8: Stationery | D8: Piece | E8: 12 | F8: 25 | G8: 100 | H8: 500
A9: P008 | B9: Stapler | C9: Stationery | D9: Piece | E9: 110 | F9: 180 | G9: 20 | H9: 90
A10: P009 | B10: Printer Paper (500 Sheets) | C10: Stationery | D10: Pack | E10: 220 | F10: 320 | G10: 30 | H10: 100
A11: P010 | B11: Highlighter Set | C11: Stationery | D11: Pack | E11: 95 | F11: 160 | G11: 20 | H11: 75
A12: P011 | B12: Office Chair | C12: Furniture | D12: Piece | E12: 3500 | F12: 5000 | G12: 8 | H12: 25
A13: P012 | B13: Study Table | C13: Furniture | D13: Piece | E13: 4200 | F13: 6200 | G13: 5 | H13: 18
... A26: P025 | B26: Desk Organizer | C26: Accessories | D26: Piece | E26: 220 | F26: 380 | G26: 15 | H26: 85

Sheet Suppliers
A1: Supplier ID | B1: Supplier Name | C1: Contact Person | D1: Phone | E1: Email | F1: GSTIN | G1: City
A2: S001 | B2: TechSource India | C2: Amit Sharma | D2: 9876543210 | E2: sales@techsource.in | F2: 27ABCDE1234F1Z5 | G2: Mumbai
A3: S002 | B3: Prime Office Supplies | C3: Neha Patel | D3: 9876543211 | E3: info@primeoffice.in | F3: 27FGHIJ5678K1Z2 | G3: Pune
A4: S003 | B4: Metro Traders | C4: Rahul Verma | D4: 9876543212 | E4: sales@metrotraders.in | F4: 29LMNOP4321Q1Z8 | G4: Bengaluru
A5: S004 | B5: Elite Electronics | C5: Sneha Joshi | D5: 9876543213 | E5: contact@eliteelectronics.in | F5: 24QRSTU9876V1Z3 | G5: Ahmedabad
A6: S005 | B6: Bright Stationers | C6: Karan Mehta | D6: 9876543214 | E6: support@brightstationers.in | F6: 07WXYZA6543B1Z7 | G6: Delhi
A7: S006 | B7: Office World Distributors | C7: Priya Nair | D7: 9876543215 | E7: sales@officeworld.in | F7: 32CDEFG1122H1Z9 | G7: Kochi
A8: S007 | B8: SmartTech Solutions | C8: Rohan Kulkarni | D8: 9876543216 | E8: info@smarttech.in | F8: 27JKLMN3344P1Z6 | G8: Nashik
A9: S008 | B9: Urban Furniture Hub | C9: Vivek Singh | D9: 9876543217 | E9: orders@urbanfurniture.in | F9: 27QRSTU7788A1Z4 | G9: Mumbai
A10: S009 | B10: Alpha Office Mart | C10: Pooja Shah | D10: 9876543218 | E10: contact@alphaoffice.in | F10: 24UVWXY5566C1Z2 | G10: Surat
A11: S010 | B11: National Supply Co. | C11: Sandeep Gupta | D11: 9876543219 | E11: sales@nationalsupply.in | F11: 09ABCDE9988D1Z1 | G11: Lucknow
A12: S011 | B12: Galaxy Wholesale | C12: Meera Iyer | D12: 9876543220 | E12: support@galaxywholesale.in | F12: 33FGHIJ7766E1Z5 | G12: Chennai
A13: S012 | B13: Zenith Business Supplies | C13: Arjun Rao | D13: 9876543221 | E13: hello@zenithsupplies.in | F13: 29KLMNO4455F1Z8 | G13: Hyderabad

Sheet Lists
A1: Customer ID | B1: Customer Name | C1: City
A2: C001 | B2: Apex Retail | C2: Mumbai
A3: C002 | B3: Bright Stores | C3: Pune
A4: C003 | B4: City Mart | C4: Nashik
A5: C004 | B5: Elite Traders | C5: Delhi
A6: C005 | B6: Future Electronics | C6: Bengaluru
A7: C006 | B7: Global Supplies | C7: Hyderabad
A8: C007 | B8: Metro Bazaar | C8: Ahmedabad
A9: C008 | B9: Nova Enterprises | C9: Chennai | I9: PO No | J9: Date | K9: Supplier | L9: Product ID | M9: Qty Purchased
A10: C009 | B10: Prime Retailers | C10: Surat
A11: C010 | B11: Sunrise Distributors | C11: Jaipur
G13: Invoice No | H13: Date | I13: Customer | J13: Product ID | K13: Qty Sold
G14: INV031 | H14: 46079 | I14: Apex Retail | J14: P003 | K14: 18
G15: INV032 | H15: 46080 | I15: Bright Stores | J15: P001 | K15: 12
G16: INV033 | H16: 46081 | I16: City Mart | J16: P009 | K16: 22
G17: INV034 | H17: 46082 | I17: Elite Traders | J17: P020 | K17: 5
G18: INV035 | H18: 46083 | I18: Future Electronics | J18: P011 | K18: 2
G19: INV036 | H19: 46084 | I19: Global Supplies | J19: P024 | K19: 90
G20: INV037 | H20: 46085 | I20: Metro Bazaar | J20: P006 | K20: 35
G21: INV038 | H21: 46086 | I21: Nova Enterprises | J21: P019 | K21: 8
G22: INV039 | H22: 46087 | I22: Prime Retailers | J22: P017 | K22: 10
G23: INV040 | H23: 46088 | I23: Sunrise Distributors | J23: P005 | K23: 20
G24: INV041 | H24: 46089 | I24: Apex Retail | J24: P023 | K24: 15
G25: INV042 | H25: 46090 | I25: Bright Stores | J25: P007 | K25: 85
... G103: INV120 | H103: 46168 | I103: Sunrise Distributors | J103: P017 | K103: 9
